CXRunner/__init__.py
CXRunner/_email.py
CXRunner/config.py
CXRunner/version.py
CXRunner/html/__init__.py
CXRunner/html/heading-en.html
CXRunner/html/heading-zh-CN.html
CXRunner/html/mail.html
CXRunner/html/notice_tmp.md
CXRunner/html/report-en.html
CXRunner/html/report-zh-CN.html
CXRunner/html/stylesheet.html
CXRunner/html/template.html
CXRunner/htmlrunner/__init__.py
CXRunner/htmlrunner/result.py
CXRunner/htmlrunner/runner.py
CXRunner/xmlrunner/__init__.py
CXRunner/xmlrunner/result.py
CXRunner/xmlrunner/runner.py
CXRunner-1.0.6.dist-info/LICENSE
CXRunner-1.0.6.dist-info/METADATA
CXRunner-1.0.6.dist-info/WHEEL
CXRunner-1.0.6.dist-info/top_level.txt
CXRunner-1.0.6.dist-info/RECORD
